{
"date": "2022-10-24",
"injuries": [
{
"player_id": 1628464,
"team_id": 1610612754,
"status": "Out"
},
{
"player_id": 1626167,
"team_id": 1610612754,
"status": "Out"
},
{
"player_id": 1629656,
"team_id": 1610612752,
"status": "Out"
},
{
"player_id": 1630624,
"team_id": 1610612752,
"status": "Out"
},
{
"player_id": 1631211,
"team_id": 1610612752,
"status": "Out"
},
{
"player_id": 1628365,
"team_id": 1610612753,
"status": "Out"
},
{
"player_id": 203914,
"team_id": 1610612753,
"status": "Out"
},
{
"player_id": 1628371,
"team_id": 1610612753,
"status": "Out"
},
{
"player_id": 1630591,
"team_id": 1610612753,
"status": "Out"
},
{
"player_id": 1629021,
"team_id": 1610612753,
"status": "Out"
},
{
"player_id": 1628997,
"team_id": 1610612748,
"status": "Out"
},
{
"player_id": 203506,
"team_id": 1610612748,
"status": "Out"
},
{
"player_id": 1630209,
"team_id": 1610612748,
"status": "Out"
},
{
"player_id": 203490,
"team_id": 1610612761,
"status": "Out"
},
{
"player_id": 203552,
"team_id": 1610612751,
"status": "Out"
},
{
"player_id": 202693,
"team_id": 1610612751,
"status": "Out"
},
{
"player_id": 203933,
"team_id": 1610612751,
"status": "Out"
},
{
"player_id": 201980,
"team_id": 1610612763,
"status": "Out"
},
{
"player_id": 1628991,
"team_id": 1610612763,
"status": "Out"
},
{
"player_id": 1630533,
"team_id": 1610612763,
"status": "Out"
},
{
"player_id": 201568,
"team_id": 1610612738,
"status": "Out"
},
{
"player_id": 1629057,
"team_id": 1610612738,
"status": "Out"
},
{
"player_id": 1628366,
"team_id": 1610612741,
"status": "Out"
},
{
"player_id": 203937,
"team_id": 1610612750,
"status": "Out"
},
{
"player_id": 1630568,
"team_id": 1610612750,
"status": "Out"
},
{
"player_id": 1631169,
"team_id": 1610612750,
"status": "Out"
},
{
"player_id": 203085,
"team_id": 1610612750,
"status": "Out"
},
{
"player_id": 1631230,
"team_id": 1610612759,
"status": "Out"
},
{
"player_id": 1631103,
"team_id": 1610612759,
"status": "Out"
},
{
"player_id": 1631160,
"team_id": 1610612759,
"status": "Out"
},
{
"player_id": 1631104,
"team_id": 1610612759,
"status": "Out"
},
{
"player_id": 1628981,
"team_id": 1610612745,
"status": "Out"
},
{
"player_id": 1630256,
"team_id": 1610612745,
"status": "Out"
},
{
"player_id": 1631102,
"team_id": 1610612745,
"status": "Out"
},
{
"player_id": 1628962,
"team_id": 1610612762,
"status": "Out"
},
{
"player_id": 1630548,
"team_id": 1610612762,
"status": "Out"
},
{
"player_id": 1630695,
"team_id": 1610612762,
"status": "Out"
},
{
"player_id": 1631221,
"team_id": 1610612743,
"status": "Out"
},
{
"player_id": 1627780,
"team_id": 1610612757,
"status": "Out"
},
{
"player_id": 1630846,
"team_id": 1610612757,
"status": "Out"
},
{
"player_id": 1630570,
"team_id": 1610612757,
"status": "Out"
},
{
"player_id": 1628963,
"team_id": 1610612765,
"status": "Out"
},
{
"player_id": 1631205,
"team_id": 1610612765,
"status": "Out"
},
{
"player_id": 202692,
"team_id": 1610612765,
"status": "Out"
},
{
"player_id": 1630296,
"team_id": 1610612765,
"status": "Out"
},
{
"player_id": 1630557,
"team_id": 1610612764,
"status": "Out"
},
{
"player_id": 202722,
"team_id": 1610612742,
"status": "Out"
},
{
"player_id": 1628373,
"team_id": 1610612742,
"status": "Out"
},
{
"player_id": 1627742,
"team_id": 1610612740,
"status": "Out"
},
{
"player_id": 1630184,
"team_id": 1610612740,
"status": "Out"
},
{
"player_id": 1630604,
"team_id": 1610612740,
"status": "Out"
},
{
"player_id": 1631116,
"team_id": 1610612744,
"status": "Out"
},
{
"player_id": 1628978,
"team_id": 1610612744,
"status": "Out"
},
{
"player_id": 2738,
"team_id": 1610612744,
"status": "Out"
},
{
"player_id": 1630237,
"team_id": 1610612744,
"status": "Out"
},
{
"player_id": 1631157,
"team_id": 1610612744,
"status": "Out"
}
]
}